{
  "path_elements": [
    {
      "type": "translation",
      "x_meters": 6.199978851636303,
      "y_meters": 6.945639991876026,
      "intermediate_handoff_radius_meters": 0.2
    },
    {
      "type": "waypoint",
      "translation_target": {
        "x_meters": 6.1703345612625755,
        "y_meters": 4.335773554390411,
        "intermediate_handoff_radius_meters": 0.2
      },
      "rotation_target": {
        "rotation_radians": 0.0,
        "profiled_rotation": false
      }
    },
    {
      "type": "rotation",
      "rotation_radians": 1.5707963267948966,
      "t_ratio": 0.618452531646705,
      "profiled_rotation": false
    },
    {
      "type": "translation",
      "x_meters": 7.088323319847506,
      "y_meters": 2.9626581884650705,
      "intermediate_handoff_radius_meters": 0.2
    }
  ],
  "constraints": {
    "end_translation_tolerance_meters": 0.076
  }
}